dynamicPip/__init__.py
dynamicPip/__main__.py
dynamicPip/dync_pip.py
dynamicPip/mirror_manager.py
dynamicPip/static_resources.py
dynamicPip/utility/__init__.py
dynamicPip/utility/meta_data_reader.py
dynamicPip/utility/toolkits.py
dynamic_pip-1.1.2.dist-info/LICENSE
dynamic_pip-1.1.2.dist-info/METADATA
dynamic_pip-1.1.2.dist-info/WHEEL
dynamic_pip-1.1.2.dist-info/top_level.txt
dynamic_pip-1.1.2.dist-info/RECORD
