Metadata-Version: 2.1
Name: dynamic-pip
Version: 1.1.2
Summary: Help users to dynamically manage python package resources
Author-email: "xin.he" <unknow@dynamic-pip.com>
License: Apache 2.0
Project-URL: Homepage, https://github.com/uguisu/dynamic-pip
Project-URL: Documentation, https://github.com/uguisu/dynamic-pip
Project-URL: Repository, https://github.com/uguisu/dynamic-pip
Project-URL: Issues, https://github.com/uguisu/dynamic-pip/issues
Keywords: dynamic,pip,packages
Classifier: Development Status :: 5 - Production/Stable
Classifier: Intended Audience :: Developers
Classifier: Programming Language :: Python :: 3.7
Classifier: Programming Language :: Python :: 3.8
Classifier: Programming Language :: Python :: 3.9
Classifier: Programming Language :: Python :: 3.10
Classifier: Programming Language :: Unix Shell
Classifier: Operating System :: OS Independent
Classifier: Topic :: Software Development
Classifier: Topic :: Software Development :: Libraries
Classifier: Topic :: Software Development :: Libraries :: Python Modules
Requires-Python: >=3.7
License-File: LICENSE
Requires-Dist: icmplib ==3.0.3
